expandpath/__init__.py
expandpath/__main__.py
expandpath/core/__init__.py
expandpath/tests/__init__.py
expandpath/tests/test_1984.py
expandpath-0.0.3.dist-info/licenses/LICENSE.txt
expandpath-0.0.3.dist-info/METADATA
expandpath-0.0.3.dist-info/WHEEL
expandpath-0.0.3.dist-info/top_level.txt
expandpath-0.0.3.dist-info/RECORD
