Metadata-Version: 2.4
Name: expandpath
Version: 0.0.3
Summary: This project expands a given path.
Author-email: Johannes <johannes.programming@gmail.com>
License: The MIT License (MIT)
Project-URL: Download, https://pypi.org/project/expandpath/#files
Project-URL: Index, https://pypi.org/project/expandpath/
Project-URL: Source, https://github.com/johannes-programming/expandpath/
Project-URL: Website, https://expandpath.johannes-programming.online/
Classifier: Development Status :: 2 - Pre-Alpha
Classifier: License :: OSI Approved :: MIT License
Classifier: Natural Language :: English
Classifier: Operating System :: OS Independent
Classifier: Programming Language :: Python
Classifier: Programming Language :: Python :: 3
Classifier: Programming Language :: Python :: 3 :: Only
Classifier: Typing :: Typed
Requires-Python: >=3.11
License-File: LICENSE.txt
Requires-Dist: click>=8.1.8
Requires-Dist: preparse>=0.0.12
Dynamic: license-file
